{
  "exam_set": "set2",
  "order": 64,
  "body": "ある企業はAWS上でウェブアプリケーションを運営しています。このアプリケーションは、1つのVPC内の2つのパブリックサブネットに配置されており、1つのパブリックサブネットにはインターネットからアクセス可能なWebサーバーが設置され、もう1つのパブリックサブネットにはデータベースサーバーが配置されています。セキュリティ担当者は、このアーキテクチャのセキュリティ強化に取り組んでいます。このウェブアプリケーションは社内専用であり、WEBサーバーへのアクセスは社内ネットワークからのみ許可される必要があります。\n\nこれらの要件を満たす最もセキュリティが高い構成はどれでしょうか。",
  "option_a": "データベースサーバーをAmazon RDS DBインスタンスに移行して、プライベートサブネットに設置する。社内ネットワークからAWS Direct Connect経由でプライベートサブネットに接続する。",
  "option_b": "WEBサーバーをプライベートサブネットに移動する。データベースサーバーをAmazon RDS DBインスタンスに移行してプライベートサブネットに設置し、プライベートサブネットのルートテーブルにおいてNATゲートウェイへのルートを設定する。",
  "option_c": "データベースサーバーとWEBサーバーをプライベートサブネットに移動する。プライベートサブネットのルートテーブルにおいてNATゲートウェイへのルートを設定する。",
  "option_d": "データベースサーバーとWEBサーバーをプライベートサブネットに移動する。社内ネットワークからAWS Direct Connect経由でプライベートサブネットに接続する。",
  "answer": "D",
  "domain": "VPC / Direct Connect",
  "explanation": {
    "key_conditions": "社内専用 / WEBサーバーへのアクセスは社内のみ / セキュリティ最高",
    "what_is_asked": "社内専用アプリをインターネットから完全に隔離してセキュリティを最大化する構成",
    "decision_axis": "セキュリティ最大 → WEB + DBをプライベートサブネット + Direct Connect（専用線でインターネット経由なし）",
    "keywords": [
      { "keyword": "社内専用 + セキュリティ最高", "pattern": "正解", "reason": "WEB + DBを両方プライベートサブネットに移動してインターネットから完全隔離。社内からはDirect Connect（専用線）でアクセス" },
      { "keyword": "NATゲートウェイ + 社内専用サーバー", "pattern": "誤り", "reason": "NATゲートウェイはプライベートEC2からインターネットへのアウトバウンド。社内専用で最高セキュリティには不要" }
    ],
    "options_analysis": [
      {
        "option": "A",
        "text": "RDBをプライベートサブネット + Direct Connect（WEBはパブリックのまま）",
        "is_correct": false,
        "reason": "WEBサーバーがパブリックサブネットに残っているためインターネットからアクセス可能。社内専用の要件を満たさない"
      },
      {
        "option": "B",
        "text": "WEB + RDBをプライベートサブネット + NATゲートウェイ",
        "is_correct": false,
        "reason": "NATゲートウェイはプライベートからインターネットへのアウトバウンド経路。社内専用でNATゲートウェイを設定する必要はなく、社内からの接続手段（VPN/Direct Connect）がない"
      },
      {
        "option": "C",
        "text": "WEB + DBをプライベートサブネット + NATゲートウェイ",
        "is_correct": false,
        "reason": "NATゲートウェイで社内からのインバウンドは実現できない。社内からアクセスするためにはVPN/Direct Connectが必要"
      },
      {
        "option": "D",
        "text": "WEB + DBをプライベートサブネット + Direct Connect",
        "is_correct": true,
        "reason": "WEBとDBを両方プライベートサブネットに移動してインターネットから完全隔離。Direct Connect（専用線）で社内ネットワークからのみアクセスを許可。最高セキュリティ構成"
      }
    ],
    "essence": "社内専用の最高セキュリティ＝WEB + DBをプライベートサブネット + Direct Connect（専用線）。NATゲートウェイは社内からの接続には使わない"
  }
}
